{
    "adri": {
        "username": "adri",
        "password": "igz86737",
        "email": "dan.adriana@cnmv.ro",
        "progress": {
            "Python": {
                "Uranus": 1
            }
        }
    },
    "adriana": {
        "username": "adriana",
        "password": "igz86737",
        "email": "dan.adriana@cnmv.ro",
        "progress": {
            "Python": {
                "Venus": 1
            }
        }
    },
    "alex": {
        "username": "alex",
        "password": "igz86737",
        "email": "niculaie.alex@cnmv.ro"
    },
    "horia": {
        "username": "horia",
        "password": "Password@2025",
        "email": "cosmiccode2025@gmail.com"
    },
    "horia2": {
        "username": "horia2",
        "password": "igz86737",
        "email": "cosmiccode2025@gmail.com"
    },
    "maria": {
        "username": "maria",
        "password": "igz86737",
        "email": "dan.adriana@cnmv.ro"
    }
}